{"cameraMode":{"drawMode":0,"name":"Shaded","section":"Shading Mode"},"sceneLighting":true,"audioPlay":false,"sceneViewState":{"m_AlwaysRefresh":false,"showFog":true,"showSkybox":true,"showFlares":true,"showImageEffects":true,"showParticleSystems":true,"showVisualEffectGraphs":true,"m_FxEnabled":true},"in2DMode":false,"pivot":{"x":4.628880023956299,"y":11.55130386352539,"z":11.051782608032227},"rotation":{"x":-0.19654406607151032,"y":0.11381156742572785,"z":0.022993767634034158,"w":0.9736407399177551},"size":10.172337532043457,"orthographic":false}